[
  {
    "NameCourse": "Java Script Avanced",
    "Image": "https://th.bing.com/th/id/OIP.7M2ozah2nfvoMu9kcYd5_AHaIA?pid=ImgDet&rs=1",
    "DateInit": "21/09/2020",
    "Description": "Java script course from basic to advanced."
  },
  {
    "NameCourse": "React",
    "Image": "https://oneteamsolutions.in/blogoneteam/wp-content/uploads/2020/05/REACT-JS-KOCHI.png",
    "DateInit": "21/09/2020",
    "Description": "React Course."
  },
  {
    "NameCourse": "Angular",
    "Image": "https://th.bing.com/th/id/OIP.HzaS8YRQE13jGeyd8DPxNAHaHa?pid=ImgDet&rs=1",
    "DateInit": "21/09/2020",
    "Description": "Lorem Ipsum e simplesmente uma simulacao de texto daeculo XVI."
  },
  {
    "NameCourse": "ASP.NET",
    "Image": "https://www.avibeweb.com/images/imagebank/ASP.NET/asp.png",
    "DateInit": "21/09/2020",
    "Description": "MVC ASP.NET web systems and Web API."
  },
  {
    "NameCourse": "SQL Server",
    "Image": "https://th.bing.com/th/id/OIP.Z86hSked6bhCCrvwCgOa_AHaD2?pid=ImgDet&rs=1",
    "DateInit": "21/09/2020",
    "Description": "Course ultilizing T-SQL for creating relational tables."
  }
]
